chimera/__init__.py
chimera/cli.py
chimera/commands/__init__.py
chimera/commands/create.py
chimera/commands/list.py
chimera/config/ports.yaml
chimera/core/__init__.py
chimera/core/port_allocator.py
chimera/core/port_scanner.py
chimera/core/template_manager.py
chimera/core/template_validator.py
chimera/templates/README.md
chimera/templates/__init__.py
chimera/templates/template.yaml.example
chimera/templates/_scaffolding/readme.j2
chimera/templates/base/backend/php/docker-compose.yml
chimera/templates/base/backend/php/template.yaml
chimera/templates/base/backend/php/docker/php/Dockerfile
chimera/templates/base/backend/php/docker/php/php.ini
chimera/templates/base/backend/php/docker/php/www.conf
chimera/templates/base/backend/php/src/Database.php
chimera/templates/base/backend/php/src/bootstrap.php
chimera/templates/base/backend/php/src/pages/home.php
chimera/templates/base/core/welcome/template.yaml
chimera/templates/base/core/welcome/docker/nginx/conf.d/default.conf
chimera/templates/base/core/welcome/nginx/conf.d/default.conf
chimera/templates/base/core/welcome/www/index.php
chimera/templates/base/core/welcome/www/welcome.html.j2
chimera/templates/base/database/mariadb/docker-compose.yml
chimera/templates/base/database/mariadb/template.yaml
chimera/templates/base/database/mysql/docker-compose.yml
chimera/templates/base/database/mysql/template.yaml
chimera/templates/base/database/postgresql/docker-compose.yml
chimera/templates/base/database/postgresql/template.yaml
chimera/templates/stacks/backend/php-web/README.md
chimera/templates/stacks/backend/php-web/docker-compose.mariadb.yml
chimera/templates/stacks/backend/php-web/docker-compose.mysql.yml
chimera/templates/stacks/backend/php-web/docker-compose.postgresql.yml
chimera/templates/stacks/backend/php-web/docker-compose.yml.j2
chimera/templates/stacks/backend/php-web/env.template
chimera/templates/stacks/backend/php-web/post_copy_readme.yaml
chimera/templates/stacks/backend/php-web/template.yaml
chimera_stack_cli-0.2.6.dist-info/licenses/LICENSE
chimera_stack_cli-0.2.6.dist-info/METADATA
chimera_stack_cli-0.2.6.dist-info/WHEEL
chimera_stack_cli-0.2.6.dist-info/entry_points.txt
chimera_stack_cli-0.2.6.dist-info/top_level.txt
chimera_stack_cli-0.2.6.dist-info/RECORD
