Metadata-Version: 2.4
Name: chimera-stack-cli
Version: 0.2.6
Summary: A template-based development environment manager
Author-email: Amir <amirofcodes20@gmail.com>
License: MIT
Project-URL: Bug Tracker, https://github.com/Amirofcodes/ChimeraStack_CLI/issues
Project-URL: Documentation, https://github.com/Amirofcodes/ChimeraStack_CLI#readme
Project-URL: Source, https://github.com/Amirofcodes/ChimeraStack_CLI
Classifier: Development Status :: 3 - Alpha
Classifier: Intended Audience :: Developers
Classifier: License :: OSI Approved :: MIT License
Classifier: Programming Language :: Python :: 3
Classifier: Programming Language :: Python :: 3.10
Classifier: Programming Language :: Python :: 3.11
Requires-Python: >=3.10
License-File: LICENSE
Requires-Dist: click>=8.0.0
Requires-Dist: python-dotenv>=0.19.0
Requires-Dist: pyyaml>=6.0.0
Requires-Dist: colorama>=0.4.4
Requires-Dist: docker>=6.0.0
Requires-Dist: rich>=13.0.0
Requires-Dist: questionary>=2.0.0
Requires-Dist: jsonschema>=4.0.0
Requires-Dist: jinja2>=3.0.0
Dynamic: license-file
